pyodide_mkdocs_theme/PMT_tools/p5/__init__.py
pyodide_mkdocs_theme/PMT_tools/vis/__init__.py
pyodide_mkdocs_theme/PMT_tools/vis_network/__init__.py
pyodide_mkdocs_theme/__init__.py
pyodide_mkdocs_theme/__main__.py
pyodide_mkdocs_theme/__version__.py
pyodide_mkdocs_theme/basthon_p5_to_pmt.py
pyodide_mkdocs_theme/pyodide_macros/__init__.py
pyodide_mkdocs_theme/pyodide_macros/exceptions.py
pyodide_mkdocs_theme/pyodide_macros/files_extractors/__init__.py
pyodide_mkdocs_theme/pyodide_macros/files_extractors/_inclusions_tools.py
pyodide_mkdocs_theme/pyodide_macros/files_extractors/base0_extractors.py
pyodide_mkdocs_theme/pyodide_macros/files_extractors/base1_contents_extractor.py
pyodide_mkdocs_theme/pyodide_macros/files_extractors/base2_inclusions.py
pyodide_mkdocs_theme/pyodide_macros/files_extractors/base3_generic_extractors.py
pyodide_mkdocs_theme/pyodide_macros/files_extractors/concrete_extractors.py
pyodide_mkdocs_theme/pyodide_macros/html_builder/__init__.py
pyodide_mkdocs_theme/pyodide_macros/html_builder/_html_builder.py
pyodide_mkdocs_theme/pyodide_macros/html_dependencies/__init__.py
pyodide_mkdocs_theme/pyodide_macros/html_dependencies/deps.py
pyodide_mkdocs_theme/pyodide_macros/html_dependencies/deps_class.py
pyodide_mkdocs_theme/pyodide_macros/indent_parser.py
pyodide_mkdocs_theme/pyodide_macros/macros/IDEs.py
pyodide_mkdocs_theme/pyodide_macros/macros/__init__.py
pyodide_mkdocs_theme/pyodide_macros/macros/figure.py
pyodide_mkdocs_theme/pyodide_macros/macros/ide_ide.py
pyodide_mkdocs_theme/pyodide_macros/macros/ide_manager.py
pyodide_mkdocs_theme/pyodide_macros/macros/ide_playground.py
pyodide_mkdocs_theme/pyodide_macros/macros/ide_py_btn.py
pyodide_mkdocs_theme/pyodide_macros/macros/ide_run_macro.py
pyodide_mkdocs_theme/pyodide_macros/macros/ide_term_ide.py
pyodide_mkdocs_theme/pyodide_macros/macros/ide_terminal.py
pyodide_mkdocs_theme/pyodide_macros/macros/ide_tester.py
pyodide_mkdocs_theme/pyodide_macros/macros/py_script.py
pyodide_mkdocs_theme-5.4.3.dist-info/LICENSE
pyodide_mkdocs_theme-5.4.3.dist-info/METADATA
pyodide_mkdocs_theme-5.4.3.dist-info/WHEEL
pyodide_mkdocs_theme-5.4.3.dist-info/entry_points.txt
pyodide_mkdocs_theme-5.4.3.dist-info/RECORD
