Metadata-Version: 2.3
Name: pyodide-mkdocs-theme
Version: 5.4.3
Summary: Package embedding the necessary tools to host pyodide, ACE editors, jQuery terminals in mkdocs documentations
License: GPL-3.0-or-later
Keywords: mkdocs,mkdocs-plugin,pyodide,IDE,terminal
Author: Frédéric Zinelli
Author-email: frederic.zinelli@gmail.com
Requires-Python: >=3.9, <4.0
Classifier: Development Status :: 5 - Production/Stable
Classifier: Environment :: Plugins
Classifier: Environment :: Web Environment
Classifier: Framework :: MkDocs
Classifier: Intended Audience :: Education
Classifier: License :: OSI Approved :: GNU General Public License v3 or later (GPLv3+)
Classifier: Programming Language :: Python
Classifier: Programming Language :: Python :: 3.9
Classifier: Programming Language :: Python :: 3.10
Classifier: Programming Language :: Python :: 3.11
Classifier: Programming Language :: Python :: 3.12
Classifier: Programming Language :: Python :: 3.13
Classifier: Programming Language :: JavaScript
Classifier: Topic :: Documentation
Classifier: Topic :: Software Development :: Documentation
Classifier: Topic :: Text Processing :: Markup :: HTML
Requires-Dist: click (<=8.2.1)
Requires-Dist: mkdocs (>=1.6)
Requires-Dist: mkdocs-macros-plugin (>=1.4)
Requires-Dist: mkdocs-material (>=9.5)
Requires-Dist: pymdown-extensions (>=10.11)
Project-URL: Bug Tracker, https://gitlab.com/frederic-zinelli/pyodide-mkdocs-theme/-/issues
Project-URL: Documentation, http://frederic-zinelli.gitlab.io/pyodide-mkdocs-theme/
Project-URL: Homepage, http://frederic-zinelli.gitlab.io/pyodide-mkdocs-theme/
Project-URL: Repository, https://gitlab.com/frederic-zinelli/pyodide-mkdocs-theme
